[
        {"name": "Work_Order", "columnNumber": 0, "double": false, "category":"word_order"},
        {"name": "Invoice", "columnNumber": 1, "double": true, "category":"invoice"},
        {"name": "Credit_Note", "columnNumber": 1, "double": true, "category":"credit_note"},
        {"name": "Date", "columnNumber": 2, "double": false, "category":"date"},
        {"name": "Confirmation_Status", "columnNumber": 3, "double": true, "category":"confirmation_status"},
        {"name": "Confirmation_Date", "columnNumber": 3, "double": true, "category":"confirmation_date"},
        {"name": "Accpac_ID", "columnNumber": 4, "double": true, "category":"accpac_id"},
        {"name": "Customer", "columnNumber": 4, "double": true, "category":"customer"},
        {"name": "Bill_To", "columnNumber": 5, "double": false, "category":"bill_to"},
        {"name": "Ship_To", "columnNumber": 6, "double": false, "category":"ship_to"},
        {"name": "Ship_Via", "columnNumber": 7, "double": true, "category":"ship_via"},
        {"name": "Terms", "columnNumber": 7, "double": true, "category":"terms"},
        {"name": "Territory", "columnNumber": 8, "double": true, "category":"territory"},
        {"name": "Salesperson", "columnNumber": 8, "double": true, "category":"salesperson"},
        {"name": "Job_Number", "columnNumber": 9, "double": true, "category":"job_number"},
        {"name": "PO_Number", "columnNumber": 9, "double": true, "category":"po_number"},
        {"name": "Serial_Number", "columnNumber": 10, "double": false, "category":"serial_number"},
        {"name": "Part_Subcategory", "columnNumber": 11, "double": false, "category":"part_subcategory"},
        {"name": "All_Parts", "columnNumber": 12, "double": false, "category":"all_parts"},
        {"name": "BO_Parts", "columnNumber": 13, "double": false, "category":"bo_parts"},
        {"name": "Invoiced", "columnNumber": 14, "double": false, "category":"invoiced"},
        {"name": "Non_Invoiced", "columnNumber": 15, "double": false, "category":"non_invoiced"}
      ]
